spiro_ip/__init__.py
spiro_ip/loader.py
spiro_ip/grains/__init__.py
spiro_ip/grains/ip.py
spiro_ip/module/__init__.py
spiro_ip/module/ip.py
spiro_ip-0.0.3.dist-info/METADATA
spiro_ip-0.0.3.dist-info/RECORD
spiro_ip-0.0.3.dist-info/WHEEL
spiro_ip-0.0.3.dist-info/entry_points.txt
spiro_ip-0.0.3.dist-info/top_level.txt
