Metadata-Version: 2.1
Name: spiro-ip
Version: 0.0.3
Summary: Salt modules for discovering and exposing minion's IP addresses
Home-page: https://gitlab.com/saltspiro/spiro-ip
Author: Jamie Bliss
Author-email: jamie@ivyleav.es
License: UNKNOWN
Project-URL: Bug Reports, https://gitlab.com/saltspiro/spiro-ip/issues
Project-URL: Tip Jar, https://ko-fi.com/astraluma
Project-URL: Source, https://gitlab.com/saltspiro/spiro-ip/
Keywords: salt saltstack
Platform: UNKNOWN
Classifier: Development Status :: 4 - Beta
Classifier: Intended Audience :: Developers
Classifier: Intended Audience :: System Administrators
Classifier: Environment :: Other Environment
Classifier: Operating System :: OS Independent
Classifier: Topic :: System :: Systems Administration
Classifier: License :: OSI Approved :: Apache Software License
Classifier: Programming Language :: Python :: 2
Classifier: Programming Language :: Python :: 2.7
Classifier: Programming Language :: Python :: 3
Classifier: Programming Language :: Python :: 3.5
Classifier: Programming Language :: Python :: 3.6
Classifier: Programming Language :: Python :: 3.7
Requires-Dist: setuptools
Requires-Dist: requests
